MANIFEST.in
README.rst
setup.py
pythonlangutil/__init__.py
pythonlangutil/access_modifiers.py
pythonlangutil/overload.py
pythonlangutil/singleton.py
pythonlangutil.egg-info/PKG-INFO
pythonlangutil.egg-info/SOURCES.txt
pythonlangutil.egg-info/dependency_links.txt
pythonlangutil.egg-info/not-zip-safe
pythonlangutil.egg-info/top_level.txt