Metadata-Version: 1.1
Name: pythonlangutil
Version: 0.1
Summary: Utilities for Python programmers with background in other languages.
Home-page: https://github.com/ehsan-keshavarzian/pythonlangutil
Author: Ehsan Keshavarzian
Author-email: ehsan985@gmail.com
License: MIT
Keywords: language util
Platform: UNKNOWN
Classifier: Development Status :: 2 - Pre-Alpha
Classifier: Intended Audience :: Developers
Classifier: License :: OSI Approved :: MIT License
Classifier: Natural Language :: English
Classifier: Programming Language :: Python :: 3
Classifier: Topic :: Software Development :: Libraries :: Python Modules
